dynamikontrol_toolkit/Body.py
dynamikontrol_toolkit/Camera.py
dynamikontrol_toolkit/Face.py
dynamikontrol_toolkit/Hand.py
dynamikontrol_toolkit/Tool.py
dynamikontrol_toolkit/__init__.py
DynamiKontrol_Toolkit-0.4.7.dist-info/METADATA
DynamiKontrol_Toolkit-0.4.7.dist-info/WHEEL
DynamiKontrol_Toolkit-0.4.7.dist-info/top_level.txt
DynamiKontrol_Toolkit-0.4.7.dist-info/RECORD
