Metadata-Version: 2.1
Name: DynamiKontrol-Toolkit
Version: 0.4.7
Summary: DynamiKontrol Toolkit
Home-page: https://github.com/TheMatrixGroup/DynamiKontrol
Author: The Matrix
Author-email: contact@m47rix.com
License: MIT
Classifier: Programming Language :: Python :: 3
Classifier: License :: OSI Approved :: MIT License
Classifier: Operating System :: OS Independent
Classifier: Topic :: System :: Hardware
Classifier: Topic :: System :: Hardware :: Hardware Drivers
Requires-Python: >=3.4.2
Requires-Dist: opencv-python (>=4.4)
Requires-Dist: mediapipe (>=0.8.9.1)
Requires-Dist: numpy (>=1.22.3)
Requires-Dist: DynamiKontrol
